tallytime/__init__.py
tallytime/__main__.py
tallytime/__version__.py
tallytime/_utils.py
tallytime/exceptions.py
tallytime/loggers.py
tallytime/settings.py
tallytime/tally_log.py
tallytime/tally_session.py
tallytime-0.1.0.dist-info/LICENSE
tallytime-0.1.0.dist-info/METADATA
tallytime-0.1.0.dist-info/WHEEL
tallytime-0.1.0.dist-info/top_level.txt
tallytime-0.1.0.dist-info/RECORD
