Metadata-Version: 2.1
Name: tallytime
Version: 0.1.0
Summary: A package for logging and timeboxing python projects
Author-email: Tyler Jang <tylerjang27@gmail.com>
License: MIT License        
Project-URL: Homepage, https://github.com/TylerJang27/tallytime
Project-URL: Bug Tracker, https://github.com/TylerJang27/tallytime/issues
Classifier: Programming Language :: Python :: 3
Classifier: License :: OSI Approved :: MIT License
Classifier: Operating System :: OS Independent
Requires-Python: >=3.7
License-File: LICENSE
